{
  "moduleCode": "GER1000",
  "title": "Quantitative Reasoning",
  "acadYear": "2017/2018",
  "department": "Office Of The Provost",
  "faculty": "NUS",
  "description": "This module aims to equip undergraduates with basic reasoning skills on using data to address real world issues. What are some potential complications to keep in mind as we plan what data to collect and how to use them to address our particular issue? When two things are related (e.g. smoking and cancer), how can we tell whether the relationship is causal (e.g. smoking causes cancer)? How can quantitative reasoning help us deal with uncertainty or elucidate complex relationships? These and other questions will be discussed using real world examples.",
  "moduleCredit": "4",
  "workload": [2, 1, 0, 3, 4],
  "semesterData": [
    {
      "semester": 1,
      "examDate": "2017-11-25T13:00+0800",
      "timetable": [
        {
          "classNo": "A01",
          "lessonType": "Tutorial",
          "weeks": [3, 5, 7, 9, 11],
          "day": "Tuesday",
          "startTime": "1000",
          "endTime": "1200",
          "venue": "AS1-0207",
          "lessonIndex": 0
        },
        {
          "classNo": "A02",
          "lessonType": "Tutorial",
          "weeks": [4, 6, 8, 10, 12],
          "day": "Tuesday",
          "startTime": "1000",
          "endTime": "1200",
          "venue": "AS1-0207",
          "lessonIndex": 1
        },
        {
          "classNo": "A03",
          "lessonType": "Tutorial",
          "weeks": [3, 5, 7, 9, 11],
          "day": "Tuesday",
          "startTime": "1200",
          "endTime": "1400",
          "venue": "AS1-0207",
          "lessonIndex": 2
        },
        {
          "classNo": "A04",
          "lessonType": "Tutorial",
          "weeks": [4, 6, 8, 10, 12],
          "day": "Tuesday",
          "startTime": "1200",
          "endTime": "1400",
          "venue": "AS1-0207",
          "lessonIndex": 3
        },
        {
          "classNo": "A07",
          "lessonType": "Tutorial",
          "weeks": [3, 5, 7, 9, 11],
          "day": "Monday",
          "startTime": "1000",
          "endTime": "1200",
          "venue": "AS1-0207",
          "lessonIndex": 4
        },
        {
          "classNo": "A08",
          "lessonType": "Tutorial",
          "weeks": [4, 6, 8, 10, 12],
          "day": "Monday",
          "startTime": "1000",
          "endTime": "1200",
          "venue": "AS1-0207",
          "lessonIndex": 5
        },
        {
          "classNo": "A09",
          "lessonType": "Tutorial",
          "weeks": [3, 5, 7, 9, 11],
          "day": "Tuesday",
          "startTime": "1900",
          "endTime": "2100",
          "venue": "AS1-0207",
          "lessonIndex": 6
        },
        {
          "classNo": "A10",
          "lessonType": "Tutorial",
          "weeks": [4, 6, 8, 10, 12],
          "day": "Tuesday",
          "startTime": "1900",
          "endTime": "2100",
          "venue": "AS1-0207",
          "lessonIndex": 7
        },
        {
          "classNo": "A11",
          "lessonType": "Tutorial",
          "weeks": [3, 5, 7, 9, 11],
          "day": "Thursday",
          "startTime": "1200",
          "endTime": "1400",
          "venue": "AS1-0207",
          "lessonIndex": 8
        },
        {
          "classNo": "A12",
          "lessonType": "Tutorial",
          "weeks": [4, 6, 8, 10, 12],
          "day": "Thursday",
          "startTime": "1200",
          "endTime": "1400",
          "venue": "AS1-0207",
          "lessonIndex": 9
        },
        {
          "classNo": "A13",
          "lessonType": "Tutorial",
          "weeks": [3, 5, 7, 9, 11],
          "day": "Thursday",
          "startTime": "1400",
          "endTime": "1600",
          "venue": "AS1-0207",
          "lessonIndex": 10
        },
        {
          "classNo": "A14",
          "lessonType": "Tutorial",
          "weeks": [4, 6, 8, 10, 12],
          "day": "Thursday",
          "startTime": "1400",
          "endTime": "1600",
          "venue": "AS1-0207",
          "lessonIndex": 11
        },
        {
          "classNo": "A15",
          "lessonType": "Tutorial",
          "weeks": [4, 6, 8, 10, 12],
          "day": "Friday",
          "startTime": "1200",
          "endTime": "1400",
          "venue": "AS1-0207",
          "lessonIndex": 12
        },
        {
          "classNo": "B01",
          "lessonType": "Tutorial",
          "weeks": [3, 5, 7, 9, 11],
          "day": "Monday",
          "startTime": "0800",
          "endTime": "1000",
          "venue": "BIZ2-0118",
          "lessonIndex": 13
        },
        {
          "classNo": "B02",
          "lessonType": "Tutorial",
          "weeks": [4, 6, 8, 10, 12],
          "day": "Monday",
          "startTime": "0800",
          "endTime": "1000",
          "venue": "BIZ2-0118",
          "lessonIndex": 14
        },
        {
          "classNo": "B03",
          "lessonType": "Tutorial",
          "weeks": [3, 5, 7, 9, 11],
          "day": "Tuesday",
          "startTime": "1400",
          "endTime": "1600",
          "venue": "BIZ2-0118",
          "lessonIndex": 15
        },
        {
          "classNo": "B04",
          "lessonType": "Tutorial",
          "weeks": [4, 6, 8, 10, 12],
          "day": "Tuesday",
          "startTime": "1400",
          "endTime": "1600",
          "venue": "BIZ2-0118",
          "lessonIndex": 16
        },
        {
          "classNo": "B05",
          "lessonType": "Tutorial",
          "weeks": [3, 5, 7, 9, 11],
          "day": "Tuesday",
          "startTime": "1600",
          "endTime": "1800",
          "venue": "BIZ2-0118",
          "lessonIndex": 17
        },
        {
          "classNo": "B06",
          "lessonType": "Tutorial",
          "weeks": [4, 6, 8, 10, 12],
          "day": "Tuesday",
          "startTime": "1600",
          "endTime": "1800",
          "venue": "BIZ2-0118",
          "lessonIndex": 18
        },
        {
          "classNo": "B07",
          "lessonType": "Tutorial",
          "weeks": [4, 6, 8, 10, 12],
          "day": "Wednesday",
          "startTime": "1600",
          "endTime": "1800",
          "venue": "BIZ2-0118",
          "lessonIndex": 19
        },
        {
          "classNo": "B08",
          "lessonType": "Tutorial",
          "weeks": [4, 6, 8, 10, 12],
          "day": "Friday",
          "startTime": "1400",
          "endTime": "1600",
          "venue": "BIZ2-0224",
          "lessonIndex": 20
        },
        {
          "classNo": "C01",
          "lessonType": "Tutorial",
          "weeks": [3, 5, 7, 9, 11],
          "day": "Tuesday",
          "startTime": "1200",
          "endTime": "1400",
          "venue": "COM2-0108",
          "lessonIndex": 21
        },
        {
          "classNo": "C02",
          "lessonType": "Tutorial",
          "weeks": [4, 6, 8, 10, 12],
          "day": "Tuesday",
          "startTime": "1200",
          "endTime": "1400",
          "venue": "COM2-0108",
          "lessonIndex": 22
        },
        {
          "classNo": "C03",
          "lessonType": "Tutorial",
          "weeks": [3, 5, 7, 9, 11],
          "day": "Thursday",
          "startTime": "1600",
          "endTime": "1800",
          "venue": "COM2-0108",
          "lessonIndex": 23
        },
        {
          "classNo": "C04",
          "lessonType": "Tutorial",
          "weeks": [4, 6, 8, 10, 12],
          "day": "Thursday",
          "startTime": "1600",
          "endTime": "1800",
          "venue": "COM2-0108",
          "lessonIndex": 24
        },
        {
          "classNo": "D01",
          "lessonType": "Tutorial",
          "weeks": [3, 5, 7, 9, 11],
          "day": "Monday",
          "startTime": "1200",
          "endTime": "1400",
          "venue": "SDE-SR14",
          "lessonIndex": 25
        },
        {
          "classNo": "D02",
          "lessonType": "Tutorial",
          "weeks": [4, 6, 8, 10, 12],
          "day": "Monday",
          "startTime": "1200",
          "endTime": "1400",
          "venue": "SDE-SR14",
          "lessonIndex": 26
        },
        {
          "classNo": "D03",
          "lessonType": "Tutorial",
          "weeks": [3, 5, 7, 9, 11],
          "day": "Thursday",
          "startTime": "0900",
          "endTime": "1100",
          "venue": "SDE-SR12",
          "lessonIndex": 27
        },
        {
          "classNo": "D04",
          "lessonType": "Tutorial",
          "weeks": [4, 6, 8, 10, 12],
          "day": "Thursday",
          "startTime": "0900",
          "endTime": "1100",
          "venue": "SDE-SR12",
          "lessonIndex": 28
        },
        {
          "classNo": "D05",
          "lessonType": "Tutorial",
          "weeks": [3, 5, 7, 9, 11],
          "day": "Thursday",
          "startTime": "1000",
          "endTime": "1200",
          "venue": "SDE-SR14",
          "lessonIndex": 29
        },
        {
          "classNo": "D06",
          "lessonType": "Tutorial",
          "weeks": [4, 6, 8, 10, 12],
          "day": "Thursday",
          "startTime": "1000",
          "endTime": "1200",
          "venue": "SDE-SR14",
          "lessonIndex": 30
        },
        {
          "classNo": "D07",
          "lessonType": "Tutorial",
          "weeks": [3, 5, 7, 9, 11],
          "day": "Thursday",
          "startTime": "1100",
          "endTime": "1300",
          "venue": "SDE-SR12",
          "lessonIndex": 31
        },
        {
          "classNo": "D08",
          "lessonType": "Tutorial",
          "weeks": [4, 6, 8, 10, 12],
          "day": "Thursday",
          "startTime": "1100",
          "endTime": "1300",
          "venue": "SDE-SR12",
          "lessonIndex": 32
        },
        {
          "classNo": "E03",
          "lessonType": "Tutorial",
          "weeks": [3, 5, 7, 9, 11],
          "day": "Monday",
          "startTime": "1200",
          "endTime": "1400",
          "venue": "E4-04-03",
          "lessonIndex": 33
        },
        {
          "classNo": "E04",
          "lessonType": "Tutorial",
          "weeks": [4, 6, 8, 10, 12],
          "day": "Monday",
          "startTime": "1200",
          "endTime": "1400",
          "venue": "E4-04-03",
          "lessonIndex": 34
        },
        {
          "classNo": "E05",
          "lessonType": "Tutorial",
          "weeks": [3, 5, 7, 9, 11],
          "day": "Monday",
          "startTime": "1400",
          "endTime": "1600",
          "venue": "E4-04-03",
          "lessonIndex": 35
        },
        {
          "classNo": "E06",
          "lessonType": "Tutorial",
          "weeks": [4, 6, 8, 10, 12],
          "day": "Monday",
          "startTime": "1400",
          "endTime": "1600",
          "venue": "E4-04-03",
          "lessonIndex": 36
        },
        {
          "classNo": "E07",
          "lessonType": "Tutorial",
          "weeks": [4, 6, 8, 10, 12],
          "day": "Wednesday",
          "startTime": "0800",
          "endTime": "1000",
          "venue": "E4-04-03",
          "lessonIndex": 37
        },
        {
          "classNo": "E08",
          "lessonType": "Tutorial",
          "weeks": [4, 6, 8, 10, 12],
          "day": "Wednesday",
          "startTime": "1200",
          "endTime": "1400",
          "venue": "E4-04-03",
          "lessonIndex": 38
        },
        {
          "classNo": "E09",
          "lessonType": "Tutorial",
          "weeks": [4, 6, 8, 10, 12],
          "day": "Wednesday",
          "startTime": "1400",
          "endTime": "1600",
          "venue": "E4-04-03",
          "lessonIndex": 39
        },
        {
          "classNo": "E10",
          "lessonType": "Tutorial",
          "weeks": [4, 6, 8, 10, 12],
          "day": "Wednesday",
          "startTime": "1600",
          "endTime": "1800",
          "venue": "E4-04-03",
          "lessonIndex": 40
        },
        {
          "classNo": "E11",
          "lessonType": "Tutorial",
          "weeks": [3, 5, 7, 9, 11],
          "day": "Thursday",
          "startTime": "0800",
          "endTime": "1000",
          "venue": "E4-04-03",
          "lessonIndex": 41
        },
        {
          "classNo": "E13",
          "lessonType": "Tutorial",
          "weeks": [3, 5, 7, 9, 11],
          "day": "Thursday",
          "startTime": "1200",
          "endTime": "1400",
          "venue": "E4-04-03",
          "lessonIndex": 42
        },
        {
          "classNo": "E14",
          "lessonType": "Tutorial",
          "weeks": [4, 6, 8, 10, 12],
          "day": "Thursday",
          "startTime": "1200",
          "endTime": "1400",
          "venue": "E4-04-03",
          "lessonIndex": 43
        },
        {
          "classNo": "S01",
          "lessonType": "Tutorial",
          "weeks": [3, 5, 7, 9, 11],
          "day": "Monday",
          "startTime": "1000",
          "endTime": "1200",
          "venue": "S16-0309",
          "lessonIndex": 44
        },
        {
          "classNo": "S02",
          "lessonType": "Tutorial",
          "weeks": [4, 6, 8, 10, 12],
          "day": "Monday",
          "startTime": "1000",
          "endTime": "1200",
          "venue": "S16-0309",
          "lessonIndex": 45
        },
        {
          "classNo": "S03",
          "lessonType": "Tutorial",
          "weeks": [3, 5, 7, 9, 11],
          "day": "Tuesday",
          "startTime": "0800",
          "endTime": "1000",
          "venue": "S16-0309",
          "lessonIndex": 46
        },
        {
          "classNo": "S04",
          "lessonType": "Tutorial",
          "weeks": [4, 6, 8, 10, 12],
          "day": "Tuesday",
          "startTime": "0800",
          "endTime": "1000",
          "venue": "S16-0309",
          "lessonIndex": 47
        },
        {
          "classNo": "S05",
          "lessonType": "Tutorial",
          "weeks": [3, 5, 7, 9, 11],
          "day": "Tuesday",
          "startTime": "1000",
          "endTime": "1200",
          "venue": "S16-0309",
          "lessonIndex": 48
        },
        {
          "classNo": "S06",
          "lessonType": "Tutorial",
          "weeks": [4, 6, 8, 10, 12],
          "day": "Tuesday",
          "startTime": "1000",
          "endTime": "1200",
          "venue": "S16-0309",
          "lessonIndex": 49
        },
        {
          "classNo": "S08",
          "lessonType": "Tutorial",
          "weeks": [4, 6, 8, 10, 12],
          "day": "Wednesday",
          "startTime": "1200",
          "endTime": "1400",
          "venue": "S16-0309",
          "lessonIndex": 50
        },
        {
          "classNo": "S09",
          "lessonType": "Tutorial",
          "weeks": [4, 6, 8, 10, 12],
          "day": "Friday",
          "startTime": "0800",
          "endTime": "1000",
          "venue": "S16-0202",
          "lessonIndex": 51
        },
        {
          "classNo": "S10",
          "lessonType": "Tutorial",
          "weeks": [3, 5, 7, 9, 11],
          "day": "Tuesday",
          "startTime": "1900",
          "endTime": "2100",
          "venue": "S16-0202",
          "lessonIndex": 52
        },
        {
          "classNo": "S11",
          "lessonType": "Tutorial",
          "weeks": [4, 6, 8, 10, 12],
          "day": "Tuesday",
          "startTime": "1900",
          "endTime": "2100",
          "venue": "S16-0202",
          "lessonIndex": 53
        },
        {
          "classNo": "U01",
          "lessonType": "Tutorial",
          "weeks": [3, 5, 7, 9, 11],
          "day": "Monday",
          "startTime": "1000",
          "endTime": "1200",
          "venue": "ERC-SR10",
          "lessonIndex": 54
        },
        {
          "classNo": "U02",
          "lessonType": "Tutorial",
          "weeks": [4, 6, 8, 10, 12],
          "day": "Monday",
          "startTime": "1000",
          "endTime": "1200",
          "venue": "ERC-SR10",
          "lessonIndex": 55
        },
        {
          "classNo": "U03",
          "lessonType": "Tutorial",
          "weeks": [3, 5, 7, 9, 11],
          "day": "Monday",
          "startTime": "1400",
          "endTime": "1600",
          "venue": "ERC-SR8",
          "lessonIndex": 56
        },
        {
          "classNo": "U04",
          "lessonType": "Tutorial",
          "weeks": [4, 6, 8, 10, 12],
          "day": "Monday",
          "startTime": "1400",
          "endTime": "1600",
          "venue": "ERC-SR8",
          "lessonIndex": 57
        },
        {
          "classNo": "U05",
          "lessonType": "Tutorial",
          "weeks": [3, 5, 7, 9, 11],
          "day": "Tuesday",
          "startTime": "1400",
          "endTime": "1600",
          "venue": "ERC-SR8",
          "lessonIndex": 58
        },
        {
          "classNo": "U06",
          "lessonType": "Tutorial",
          "weeks": [4, 6, 8, 10, 12],
          "day": "Tuesday",
          "startTime": "1400",
          "endTime": "1600",
          "venue": "ERC-SR8",
          "lessonIndex": 59
        },
        {
          "classNo": "U07",
          "lessonType": "Tutorial",
          "weeks": [4, 6, 8, 10, 12],
          "day": "Wednesday",
          "startTime": "1100",
          "endTime": "1300",
          "venue": "ERC-GLR",
          "lessonIndex": 60
        },
        {
          "classNo": "U08",
          "lessonType": "Tutorial",
          "weeks": [4, 6, 8, 10, 12],
          "day": "Wednesday",
          "startTime": "1300",
          "endTime": "1500",
          "venue": "ERC-GLR",
          "lessonIndex": 61
        },
        {
          "classNo": "U09",
          "lessonType": "Tutorial",
          "weeks": [3, 5, 7, 9, 11],
          "day": "Thursday",
          "startTime": "1400",
          "endTime": "1600",
          "venue": "ERC-SR10",
          "lessonIndex": 62
        },
        {
          "classNo": "U10",
          "lessonType": "Tutorial",
          "weeks": [4, 6, 8, 10, 12],
          "day": "Thursday",
          "startTime": "1400",
          "endTime": "1600",
          "venue": "ERC-SR10",
          "lessonIndex": 63
        },
        {
          "classNo": "U11",
          "lessonType": "Tutorial",
          "weeks": [4, 6, 8, 10, 12],
          "day": "Friday",
          "startTime": "1200",
          "endTime": "1400",
          "venue": "ERC-SR10",
          "lessonIndex": 64
        },
        {
          "classNo": "U12",
          "lessonType": "Tutorial",
          "weeks": [4, 6, 8, 10, 12],
          "day": "Friday",
          "startTime": "1600",
          "endTime": "1800",
          "venue": "ERC-SR10",
          "lessonIndex": 65
        },
        {
          "classNo": "U13",
          "lessonType": "Tutorial",
          "weeks": [4, 6, 8, 10, 12],
          "day": "Wednesday",
          "startTime": "1400",
          "endTime": "1600",
          "venue": "ERC-SR10",
          "lessonIndex": 66
        },
        {
          "classNo": "U14",
          "lessonType": "Tutorial",
          "weeks": [4, 6, 8, 10, 12],
          "day": "Friday",
          "startTime": "1000",
          "endTime": "1200",
          "venue": "ERC-SR8",
          "lessonIndex": 67
        }
      ]
    },
    {
      "semester": 2,
      "examDate": "2018-04-28T13:00+0800",
      "timetable": [
        {
          "classNo": "A01",
          "lessonType": "Tutorial",
          "weeks": [3, 5, 7, 9, 11],
          "day": "Monday",
          "startTime": "1000",
          "endTime": "1200",
          "venue": "AS1-0207",
          "lessonIndex": 0
        },
        {
          "classNo": "A02",
          "lessonType": "Tutorial",
          "weeks": [4, 6, 8, 10, 12],
          "day": "Monday",
          "startTime": "1000",
          "endTime": "1200",
          "venue": "AS1-0207",
          "lessonIndex": 1
        },
        {
          "classNo": "A03",
          "lessonType": "Tutorial",
          "weeks": [3, 5, 7, 9, 11],
          "day": "Monday",
          "startTime": "1200",
          "endTime": "1400",
          "venue": "AS1-0207",
          "lessonIndex": 2
        },
        {
          "classNo": "A04",
          "lessonType": "Tutorial",
          "weeks": [4, 6, 8, 10, 12],
          "day": "Monday",
          "startTime": "1200",
          "endTime": "1400",
          "venue": "AS1-0207",
          "lessonIndex": 3
        },
        {
          "classNo": "A05",
          "lessonType": "Tutorial",
          "weeks": [3, 5, 7, 9, 11],
          "day": "Monday",
          "startTime": "1400",
          "endTime": "1600",
          "venue": "AS1-0207",
          "lessonIndex": 4
        },
        {
          "classNo": "A06",
          "lessonType": "Tutorial",
          "weeks": [4, 6, 8, 10, 12],
          "day": "Monday",
          "startTime": "1400",
          "endTime": "1600",
          "venue": "AS1-0207",
          "lessonIndex": 5
        },
        {
          "classNo": "A07",
          "lessonType": "Tutorial",
          "weeks": [3, 5, 7, 9, 11],
          "day": "Tuesday",
          "startTime": "1000",
          "endTime": "1200",
          "venue": "AS1-0207",
          "lessonIndex": 6
        },
        {
          "classNo": "A08",
          "lessonType": "Tutorial",
          "weeks": [4, 6, 8, 10, 12],
          "day": "Tuesday",
          "startTime": "1000",
          "endTime": "1200",
          "venue": "AS1-0207",
          "lessonIndex": 7
        },
        {
          "classNo": "A09",
          "lessonType": "Tutorial",
          "weeks": [3, 5, 7, 9, 11],
          "day": "Tuesday",
          "startTime": "1200",
          "endTime": "1400",
          "venue": "AS1-0207",
          "lessonIndex": 8
        },
        {
          "classNo": "A10",
          "lessonType": "Tutorial",
          "weeks": [4, 6, 8, 10, 12],
          "day": "Tuesday",
          "startTime": "1200",
          "endTime": "1400",
          "venue": "AS1-0207",
          "lessonIndex": 9
        },
        {
          "classNo": "A11",
          "lessonType": "Tutorial",
          "weeks": [3, 5, 7, 9, 11],
          "day": "Tuesday",
          "startTime": "1400",
          "endTime": "1600",
          "venue": "AS1-0207",
          "lessonIndex": 10
        },
        {
          "classNo": "A12",
          "lessonType": "Tutorial",
          "weeks": [4, 6, 8, 10, 12],
          "day": "Tuesday",
          "startTime": "1400",
          "endTime": "1600",
          "venue": "AS1-0207",
          "lessonIndex": 11
        },
        {
          "classNo": "A13",
          "lessonType": "Tutorial",
          "weeks": [3, 5, 7, 9, 11],
          "day": "Tuesday",
          "startTime": "1600",
          "endTime": "1800",
          "venue": "AS1-0207",
          "lessonIndex": 12
        },
        {
          "classNo": "A14",
          "lessonType": "Tutorial",
          "weeks": [4, 6, 8, 10, 12],
          "day": "Tuesday",
          "startTime": "1600",
          "endTime": "1800",
          "venue": "AS1-0207",
          "lessonIndex": 13
        },
        {
          "classNo": "A17",
          "lessonType": "Tutorial",
          "weeks": [3, 5, 7, 9, 11],
          "day": "Wednesday",
          "startTime": "0800",
          "endTime": "1000",
          "venue": "AS1-0207",
          "lessonIndex": 14
        },
        {
          "classNo": "A18",
          "lessonType": "Tutorial",
          "weeks": [4, 6, 8, 10, 12],
          "day": "Wednesday",
          "startTime": "0800",
          "endTime": "1000",
          "venue": "AS1-0207",
          "lessonIndex": 15
        },
        {
          "classNo": "A19",
          "lessonType": "Tutorial",
          "weeks": [3, 5, 7, 9, 11],
          "day": "Wednesday",
          "startTime": "1000",
          "endTime": "1200",
          "venue": "AS1-0207",
          "lessonIndex": 16
        },
        {
          "classNo": "A20",
          "lessonType": "Tutorial",
          "weeks": [4, 6, 8, 10, 12],
          "day": "Wednesday",
          "startTime": "1000",
          "endTime": "1200",
          "venue": "AS1-0207",
          "lessonIndex": 17
        },
        {
          "classNo": "A21",
          "lessonType": "Tutorial",
          "weeks": [3, 5, 7, 9, 11],
          "day": "Wednesday",
          "startTime": "1200",
          "endTime": "1400",
          "venue": "AS1-0207",
          "lessonIndex": 18
        },
        {
          "classNo": "A22",
          "lessonType": "Tutorial",
          "weeks": [4, 6, 8, 10, 12],
          "day": "Wednesday",
          "startTime": "1200",
          "endTime": "1400",
          "venue": "AS1-0207",
          "lessonIndex": 19
        },
        {
          "classNo": "A23",
          "lessonType": "Tutorial",
          "weeks": [3, 5, 7, 9, 11],
          "day": "Wednesday",
          "startTime": "1400",
          "endTime": "1600",
          "venue": "AS1-0207",
          "lessonIndex": 20
        },
        {
          "classNo": "A24",
          "lessonType": "Tutorial",
          "weeks": [4, 6, 8, 10, 12],
          "day": "Wednesday",
          "startTime": "1400",
          "endTime": "1600",
          "venue": "AS1-0207",
          "lessonIndex": 21
        },
        {
          "classNo": "A25",
          "lessonType": "Tutorial",
          "weeks": [3, 5, 7, 9, 11],
          "day": "Wednesday",
          "startTime": "1600",
          "endTime": "1800",
          "venue": "AS1-0207",
          "lessonIndex": 22
        },
        {
          "classNo": "A26",
          "lessonType": "Tutorial",
          "weeks": [4, 6, 8, 10, 12],
          "day": "Wednesday",
          "startTime": "1600",
          "endTime": "1800",
          "venue": "AS1-0207",
          "lessonIndex": 23
        },
        {
          "classNo": "A27",
          "lessonType": "Tutorial",
          "weeks": [4, 6, 8, 10, 12],
          "day": "Thursday",
          "startTime": "1000",
          "endTime": "1200",
          "venue": "AS1-0207",
          "lessonIndex": 24
        },
        {
          "classNo": "A28",
          "lessonType": "Tutorial",
          "weeks": [4, 6, 8, 10, 12],
          "day": "Thursday",
          "startTime": "1200",
          "endTime": "1400",
          "venue": "AS1-0207",
          "lessonIndex": 25
        },
        {
          "classNo": "A29",
          "lessonType": "Tutorial",
          "weeks": [4, 6, 8, 10, 12],
          "day": "Thursday",
          "startTime": "1400",
          "endTime": "1600",
          "venue": "AS1-0207",
          "lessonIndex": 26
        },
        {
          "classNo": "A30",
          "lessonType": "Tutorial",
          "weeks": [4, 6, 8, 10, 12],
          "day": "Thursday",
          "startTime": "1600",
          "endTime": "1800",
          "venue": "AS1-0207",
          "lessonIndex": 27
        },
        {
          "classNo": "B01",
          "lessonType": "Tutorial",
          "weeks": [3, 5, 7, 9, 11],
          "day": "Monday",
          "startTime": "1000",
          "endTime": "1200",
          "venue": "BIZ2-0118",
          "lessonIndex": 28
        },
        {
          "classNo": "B02",
          "lessonType": "Tutorial",
          "weeks": [4, 6, 8, 10, 12],
          "day": "Monday",
          "startTime": "1000",
          "endTime": "1200",
          "venue": "BIZ2-0118",
          "lessonIndex": 29
        },
        {
          "classNo": "B03",
          "lessonType": "Tutorial",
          "weeks": [3, 5, 7, 9, 11],
          "day": "Tuesday",
          "startTime": "1400",
          "endTime": "1600",
          "venue": "BIZ2-0118",
          "lessonIndex": 30
        },
        {
          "classNo": "B04",
          "lessonType": "Tutorial",
          "weeks": [4, 6, 8, 10, 12],
          "day": "Tuesday",
          "startTime": "1400",
          "endTime": "1600",
          "venue": "BIZ2-0118",
          "lessonIndex": 31
        },
        {
          "classNo": "B05",
          "lessonType": "Tutorial",
          "weeks": [3, 5, 7, 9, 11],
          "day": "Wednesday",
          "startTime": "1000",
          "endTime": "1200",
          "venue": "BIZ2-0118",
          "lessonIndex": 32
        },
        {
          "classNo": "B06",
          "lessonType": "Tutorial",
          "weeks": [4, 6, 8, 10, 12],
          "day": "Wednesday",
          "startTime": "1000",
          "endTime": "1200",
          "venue": "BIZ2-0118",
          "lessonIndex": 33
        },
        {
          "classNo": "B07",
          "lessonType": "Tutorial",
          "weeks": [3, 5, 7, 9, 11],
          "day": "Wednesday",
          "startTime": "1400",
          "endTime": "1600",
          "venue": "BIZ2-0118",
          "lessonIndex": 34
        },
        {
          "classNo": "B08",
          "lessonType": "Tutorial",
          "weeks": [4, 6, 8, 10, 12],
          "day": "Wednesday",
          "startTime": "1400",
          "endTime": "1600",
          "venue": "BIZ2-0118",
          "lessonIndex": 35
        },
        {
          "classNo": "B09",
          "lessonType": "Tutorial",
          "weeks": [3, 5, 7, 9, 11],
          "day": "Tuesday",
          "startTime": "1200",
          "endTime": "1400",
          "venue": "BIZ2-0118",
          "lessonIndex": 36
        },
        {
          "classNo": "B10",
          "lessonType": "Tutorial",
          "weeks": [4, 6, 8, 10, 12],
          "day": "Tuesday",
          "startTime": "1200",
          "endTime": "1400",
          "venue": "BIZ2-0118",
          "lessonIndex": 37
        },
        {
          "classNo": "B11",
          "lessonType": "Tutorial",
          "weeks": [3, 5, 7, 9, 11],
          "day": "Wednesday",
          "startTime": "1600",
          "endTime": "1800",
          "venue": "BIZ2-0118",
          "lessonIndex": 38
        },
        {
          "classNo": "B12",
          "lessonType": "Tutorial",
          "weeks": [4, 6, 8, 10, 12],
          "day": "Wednesday",
          "startTime": "1600",
          "endTime": "1800",
          "venue": "BIZ2-0118",
          "lessonIndex": 39
        },
        {
          "classNo": "B13",
          "lessonType": "Tutorial",
          "weeks": [4, 6, 8, 10, 12],
          "day": "Thursday",
          "startTime": "0800",
          "endTime": "1000",
          "venue": "BIZ2-0118",
          "lessonIndex": 40
        },
        {
          "classNo": "B14",
          "lessonType": "Tutorial",
          "weeks": [4, 6, 8, 10, 12],
          "day": "Thursday",
          "startTime": "1200",
          "endTime": "1400",
          "venue": "BIZ2-0224",
          "lessonIndex": 41
        },
        {
          "classNo": "B15",
          "lessonType": "Tutorial",
          "weeks": [4, 6, 8, 10, 12],
          "day": "Thursday",
          "startTime": "1200",
          "endTime": "1400",
          "venue": "BIZ2-0118",
          "lessonIndex": 42
        },
        {
          "classNo": "B16",
          "lessonType": "Tutorial",
          "weeks": [4, 6, 8, 10, 12],
          "day": "Thursday",
          "startTime": "1600",
          "endTime": "1800",
          "venue": "BIZ2-0224",
          "lessonIndex": 43
        },
        {
          "classNo": "B17",
          "lessonType": "Tutorial",
          "weeks": [4, 6, 8, 10, 12],
          "day": "Thursday",
          "startTime": "1600",
          "endTime": "1800",
          "venue": "BIZ2-0118",
          "lessonIndex": 44
        },
        {
          "classNo": "C01",
          "lessonType": "Tutorial",
          "weeks": [3, 5, 7, 9, 11],
          "day": "Monday",
          "startTime": "1200",
          "endTime": "1400",
          "venue": "COM2-0108",
          "lessonIndex": 45
        },
        {
          "classNo": "C02",
          "lessonType": "Tutorial",
          "weeks": [4, 6, 8, 10, 12],
          "day": "Monday",
          "startTime": "1200",
          "endTime": "1400",
          "venue": "COM2-0108",
          "lessonIndex": 46
        },
        {
          "classNo": "C03",
          "lessonType": "Tutorial",
          "weeks": [3, 5, 7, 9, 11],
          "day": "Tuesday",
          "startTime": "1600",
          "endTime": "1800",
          "venue": "COM2-0108",
          "lessonIndex": 47
        },
        {
          "classNo": "C04",
          "lessonType": "Tutorial",
          "weeks": [4, 6, 8, 10, 12],
          "day": "Tuesday",
          "startTime": "1600",
          "endTime": "1800",
          "venue": "COM2-0108",
          "lessonIndex": 48
        },
        {
          "classNo": "C05",
          "lessonType": "Tutorial",
          "weeks": [4, 6, 8, 10, 12],
          "day": "Thursday",
          "startTime": "1000",
          "endTime": "1200",
          "venue": "COM2-0108",
          "lessonIndex": 49
        },
        {
          "classNo": "C06",
          "lessonType": "Tutorial",
          "weeks": [4, 6, 8, 10, 12],
          "day": "Thursday",
          "startTime": "1400",
          "endTime": "1600",
          "venue": "COM2-0108",
          "lessonIndex": 50
        },
        {
          "classNo": "D01",
          "lessonType": "Tutorial",
          "weeks": [3, 5, 7, 9, 11],
          "day": "Monday",
          "startTime": "1100",
          "endTime": "1300",
          "venue": "SDE-SR14",
          "lessonIndex": 51
        },
        {
          "classNo": "D02",
          "lessonType": "Tutorial",
          "weeks": [4, 6, 8, 10, 12],
          "day": "Monday",
          "startTime": "1100",
          "endTime": "1300",
          "venue": "SDE-SR14",
          "lessonIndex": 52
        },
        {
          "classNo": "D03",
          "lessonType": "Tutorial",
          "weeks": [3, 5, 7, 9, 11],
          "day": "Monday",
          "startTime": "1300",
          "endTime": "1500",
          "venue": "SDE-SR12",
          "lessonIndex": 53
        },
        {
          "classNo": "D04",
          "lessonType": "Tutorial",
          "weeks": [4, 6, 8, 10, 12],
          "day": "Monday",
          "startTime": "1300",
          "endTime": "1500",
          "venue": "SDE-SR12",
          "lessonIndex": 54
        },
        {
          "classNo": "D05",
          "lessonType": "Tutorial",
          "weeks": [3, 5, 7, 9, 11],
          "day": "Tuesday",
          "startTime": "0900",
          "endTime": "1100",
          "venue": "SDE-SR14",
          "lessonIndex": 55
        },
        {
          "classNo": "D06",
          "lessonType": "Tutorial",
          "weeks": [4, 6, 8, 10, 12],
          "day": "Tuesday",
          "startTime": "0900",
          "endTime": "1100",
          "venue": "SDE-SR14",
          "lessonIndex": 56
        },
        {
          "classNo": "D07",
          "lessonType": "Tutorial",
          "weeks": [3, 5, 7, 9, 11],
          "day": "Tuesday",
          "startTime": "0900",
          "endTime": "1100",
          "venue": "SDE-SR12",
          "lessonIndex": 57
        },
        {
          "classNo": "D08",
          "lessonType": "Tutorial",
          "weeks": [4, 6, 8, 10, 12],
          "day": "Tuesday",
          "startTime": "0900",
          "endTime": "1100",
          "venue": "SDE-SR12",
          "lessonIndex": 58
        },
        {
          "classNo": "D09",
          "lessonType": "Tutorial",
          "weeks": [4, 6, 8, 10, 12],
          "day": "Thursday",
          "startTime": "1100",
          "endTime": "1300",
          "venue": "SDE-SR12",
          "lessonIndex": 59
        },
        {
          "classNo": "E01",
          "lessonType": "Tutorial",
          "weeks": [3, 5, 7, 9, 11],
          "day": "Monday",
          "startTime": "0800",
          "endTime": "1000",
          "venue": "E1-06-16",
          "lessonIndex": 60
        },
        {
          "classNo": "E02",
          "lessonType": "Tutorial",
          "weeks": [4, 6, 8, 10, 12],
          "day": "Monday",
          "startTime": "0800",
          "endTime": "1000",
          "venue": "E1-06-16",
          "lessonIndex": 61
        },
        {
          "classNo": "E03",
          "lessonType": "Tutorial",
          "weeks": [3, 5, 7, 9, 11],
          "day": "Monday",
          "startTime": "1000",
          "endTime": "1200",
          "venue": "E1-06-16",
          "lessonIndex": 62
        },
        {
          "classNo": "E04",
          "lessonType": "Tutorial",
          "weeks": [4, 6, 8, 10, 12],
          "day": "Monday",
          "startTime": "1000",
          "endTime": "1200",
          "venue": "E1-06-16",
          "lessonIndex": 63
        },
        {
          "classNo": "E05",
          "lessonType": "Tutorial",
          "weeks": [3, 5, 7, 9, 11],
          "day": "Monday",
          "startTime": "1200",
          "endTime": "1400",
          "venue": "E1-06-16",
          "lessonIndex": 64
        },
        {
          "classNo": "E06",
          "lessonType": "Tutorial",
          "weeks": [4, 6, 8, 10, 12],
          "day": "Monday",
          "startTime": "1200",
          "endTime": "1400",
          "venue": "E1-06-16",
          "lessonIndex": 65
        },
        {
          "classNo": "E07",
          "lessonType": "Tutorial",
          "weeks": [3, 5, 7, 9, 11],
          "day": "Monday",
          "startTime": "1400",
          "endTime": "1600",
          "venue": "E1-06-16",
          "lessonIndex": 66
        },
        {
          "classNo": "E08",
          "lessonType": "Tutorial",
          "weeks": [4, 6, 8, 10, 12],
          "day": "Monday",
          "startTime": "1400",
          "endTime": "1600",
          "venue": "E1-06-16",
          "lessonIndex": 67
        },
        {
          "classNo": "E09",
          "lessonType": "Tutorial",
          "weeks": [3, 5, 7, 9, 11],
          "day": "Tuesday",
          "startTime": "0800",
          "endTime": "1000",
          "venue": "E1-06-16",
          "lessonIndex": 68
        },
        {
          "classNo": "E10",
          "lessonType": "Tutorial",
          "weeks": [4, 6, 8, 10, 12],
          "day": "Tuesday",
          "startTime": "0800",
          "endTime": "1000",
          "venue": "E1-06-16",
          "lessonIndex": 69
        },
        {
          "classNo": "E11",
          "lessonType": "Tutorial",
          "weeks": [3, 5, 7, 9, 11],
          "day": "Tuesday",
          "startTime": "1000",
          "endTime": "1200",
          "venue": "E1-06-16",
          "lessonIndex": 70
        },
        {
          "classNo": "E12",
          "lessonType": "Tutorial",
          "weeks": [4, 6, 8, 10, 12],
          "day": "Tuesday",
          "startTime": "1000",
          "endTime": "1200",
          "venue": "E1-06-16",
          "lessonIndex": 71
        },
        {
          "classNo": "E13",
          "lessonType": "Tutorial",
          "weeks": [3, 5, 7, 9, 11],
          "day": "Tuesday",
          "startTime": "1200",
          "endTime": "1400",
          "venue": "E1-06-16",
          "lessonIndex": 72
        },
        {
          "classNo": "E14",
          "lessonType": "Tutorial",
          "weeks": [4, 6, 8, 10, 12],
          "day": "Tuesday",
          "startTime": "1200",
          "endTime": "1400",
          "venue": "E1-06-16",
          "lessonIndex": 73
        },
        {
          "classNo": "E15",
          "lessonType": "Tutorial",
          "weeks": [3, 5, 7, 9, 11],
          "day": "Tuesday",
          "startTime": "1400",
          "endTime": "1600",
          "venue": "E1-06-16",
          "lessonIndex": 74
        },
        {
          "classNo": "E16",
          "lessonType": "Tutorial",
          "weeks": [4, 6, 8, 10, 12],
          "day": "Tuesday",
          "startTime": "1400",
          "endTime": "1600",
          "venue": "E1-06-16",
          "lessonIndex": 75
        },
        {
          "classNo": "E17",
          "lessonType": "Tutorial",
          "weeks": [3, 5, 7, 9, 11],
          "day": "Tuesday",
          "startTime": "1600",
          "endTime": "1800",
          "venue": "E1-06-16",
          "lessonIndex": 76
        },
        {
          "classNo": "E18",
          "lessonType": "Tutorial",
          "weeks": [4, 6, 8, 10, 12],
          "day": "Tuesday",
          "startTime": "1600",
          "endTime": "1800",
          "venue": "E1-06-16",
          "lessonIndex": 77
        },
        {
          "classNo": "E19",
          "lessonType": "Tutorial",
          "weeks": [3, 5, 7, 9, 11],
          "day": "Wednesday",
          "startTime": "1000",
          "endTime": "1200",
          "venue": "E1-06-16",
          "lessonIndex": 78
        },
        {
          "classNo": "E20",
          "lessonType": "Tutorial",
          "weeks": [4, 6, 8, 10, 12],
          "day": "Wednesday",
          "startTime": "1000",
          "endTime": "1200",
          "venue": "E1-06-16",
          "lessonIndex": 79
        },
        {
          "classNo": "E21",
          "lessonType": "Tutorial",
          "weeks": [3, 5, 7, 9, 11],
          "day": "Wednesday",
          "startTime": "1400",
          "endTime": "1600",
          "venue": "E1-06-16",
          "lessonIndex": 80
        },
        {
          "classNo": "E22",
          "lessonType": "Tutorial",
          "weeks": [4, 6, 8, 10, 12],
          "day": "Wednesday",
          "startTime": "1400",
          "endTime": "1600",
          "venue": "E1-06-16",
          "lessonIndex": 81
        },
        {
          "classNo": "E23",
          "lessonType": "Tutorial",
          "weeks": [4, 6, 8, 10, 12],
          "day": "Thursday",
          "startTime": "1200",
          "endTime": "1400",
          "venue": "E1-06-16",
          "lessonIndex": 82
        },
        {
          "classNo": "E24",
          "lessonType": "Tutorial",
          "weeks": [4, 6, 8, 10, 12],
          "day": "Thursday",
          "startTime": "1400",
          "endTime": "1600",
          "venue": "E1-06-16",
          "lessonIndex": 83
        },
        {
          "classNo": "S01",
          "lessonType": "Tutorial",
          "weeks": [3, 5, 7, 9, 11],
          "day": "Monday",
          "startTime": "0800",
          "endTime": "1000",
          "venue": "S16-0309",
          "lessonIndex": 84
        },
        {
          "classNo": "S02",
          "lessonType": "Tutorial",
          "weeks": [4, 6, 8, 10, 12],
          "day": "Monday",
          "startTime": "0800",
          "endTime": "1000",
          "venue": "S16-0309",
          "lessonIndex": 85
        },
        {
          "classNo": "S03",
          "lessonType": "Tutorial",
          "weeks": [3, 5, 7, 9, 11],
          "day": "Monday",
          "startTime": "1000",
          "endTime": "1200",
          "venue": "S16-0309",
          "lessonIndex": 86
        },
        {
          "classNo": "S04",
          "lessonType": "Tutorial",
          "weeks": [4, 6, 8, 10, 12],
          "day": "Monday",
          "startTime": "1000",
          "endTime": "1200",
          "venue": "S16-0309",
          "lessonIndex": 87
        },
        {
          "classNo": "S05",
          "lessonType": "Tutorial",
          "weeks": [3, 5, 7, 9, 11],
          "day": "Monday",
          "startTime": "1400",
          "endTime": "1600",
          "venue": "S16-0309",
          "lessonIndex": 88
        },
        {
          "classNo": "S06",
          "lessonType": "Tutorial",
          "weeks": [4, 6, 8, 10, 12],
          "day": "Monday",
          "startTime": "1400",
          "endTime": "1600",
          "venue": "S16-0309",
          "lessonIndex": 89
        },
        {
          "classNo": "S07",
          "lessonType": "Tutorial",
          "weeks": [3, 5, 7, 9, 11],
          "day": "Tuesday",
          "startTime": "0800",
          "endTime": "1000",
          "venue": "S16-0309",
          "lessonIndex": 90
        },
        {
          "classNo": "S08",
          "lessonType": "Tutorial",
          "weeks": [4, 6, 8, 10, 12],
          "day": "Tuesday",
          "startTime": "0800",
          "endTime": "1000",
          "venue": "S16-0309",
          "lessonIndex": 91
        },
        {
          "classNo": "S09",
          "lessonType": "Tutorial",
          "weeks": [3, 5, 7, 9, 11],
          "day": "Tuesday",
          "startTime": "1000",
          "endTime": "1200",
          "venue": "S16-0309",
          "lessonIndex": 92
        },
        {
          "classNo": "S10",
          "lessonType": "Tutorial",
          "weeks": [4, 6, 8, 10, 12],
          "day": "Tuesday",
          "startTime": "1000",
          "endTime": "1200",
          "venue": "S16-0309",
          "lessonIndex": 93
        },
        {
          "classNo": "S11",
          "lessonType": "Tutorial",
          "weeks": [3, 5, 7, 9, 11],
          "day": "Tuesday",
          "startTime": "1200",
          "endTime": "1400",
          "venue": "S16-0309",
          "lessonIndex": 94
        },
        {
          "classNo": "S12",
          "lessonType": "Tutorial",
          "weeks": [4, 6, 8, 10, 12],
          "day": "Tuesday",
          "startTime": "1200",
          "endTime": "1400",
          "venue": "S16-0309",
          "lessonIndex": 95
        },
        {
          "classNo": "S13",
          "lessonType": "Tutorial",
          "weeks": [3, 5, 7, 9, 11],
          "day": "Tuesday",
          "startTime": "1400",
          "endTime": "1600",
          "venue": "S16-0309",
          "lessonIndex": 96
        },
        {
          "classNo": "S14",
          "lessonType": "Tutorial",
          "weeks": [4, 6, 8, 10, 12],
          "day": "Tuesday",
          "startTime": "1400",
          "endTime": "1600",
          "venue": "S16-0309",
          "lessonIndex": 97
        },
        {
          "classNo": "S15",
          "lessonType": "Tutorial",
          "weeks": [3, 5, 7, 9, 11],
          "day": "Wednesday",
          "startTime": "0800",
          "endTime": "1000",
          "venue": "S16-0309",
          "lessonIndex": 98
        },
        {
          "classNo": "S16",
          "lessonType": "Tutorial",
          "weeks": [4, 6, 8, 10, 12],
          "day": "Wednesday",
          "startTime": "0800",
          "endTime": "1000",
          "venue": "S16-0309",
          "lessonIndex": 99
        },
        {
          "classNo": "S17",
          "lessonType": "Tutorial",
          "weeks": [3, 5, 7, 9, 11],
          "day": "Wednesday",
          "startTime": "1000",
          "endTime": "1200",
          "venue": "S16-0309",
          "lessonIndex": 100
        },
        {
          "classNo": "S18",
          "lessonType": "Tutorial",
          "weeks": [4, 6, 8, 10, 12],
          "day": "Wednesday",
          "startTime": "1000",
          "endTime": "1200",
          "venue": "S16-0309",
          "lessonIndex": 101
        },
        {
          "classNo": "S19",
          "lessonType": "Tutorial",
          "weeks": [3, 5, 7, 9, 11],
          "day": "Wednesday",
          "startTime": "1200",
          "endTime": "1400",
          "venue": "S16-0309",
          "lessonIndex": 102
        },
        {
          "classNo": "S20",
          "lessonType": "Tutorial",
          "weeks": [4, 6, 8, 10, 12],
          "day": "Wednesday",
          "startTime": "1200",
          "endTime": "1400",
          "venue": "S16-0309",
          "lessonIndex": 103
        },
        {
          "classNo": "S21",
          "lessonType": "Tutorial",
          "weeks": [3, 5, 7, 9, 11],
          "day": "Wednesday",
          "startTime": "1400",
          "endTime": "1600",
          "venue": "S16-0309",
          "lessonIndex": 104
        },
        {
          "classNo": "S22",
          "lessonType": "Tutorial",
          "weeks": [4, 6, 8, 10, 12],
          "day": "Wednesday",
          "startTime": "1400",
          "endTime": "1600",
          "venue": "S16-0309",
          "lessonIndex": 105
        },
        {
          "classNo": "S23",
          "lessonType": "Tutorial",
          "weeks": [3, 5, 7, 9, 11],
          "day": "Wednesday",
          "startTime": "1600",
          "endTime": "1800",
          "venue": "S16-0309",
          "lessonIndex": 106
        },
        {
          "classNo": "S24",
          "lessonType": "Tutorial",
          "weeks": [4, 6, 8, 10, 12],
          "day": "Wednesday",
          "startTime": "1600",
          "endTime": "1800",
          "venue": "S16-0309",
          "lessonIndex": 107
        },
        {
          "classNo": "S25",
          "lessonType": "Tutorial",
          "weeks": [4, 6, 8, 10, 12],
          "day": "Thursday",
          "startTime": "0800",
          "endTime": "1000",
          "venue": "S16-0309",
          "lessonIndex": 108
        },
        {
          "classNo": "S26",
          "lessonType": "Tutorial",
          "weeks": [4, 6, 8, 10, 12],
          "day": "Thursday",
          "startTime": "1000",
          "endTime": "1200",
          "venue": "S16-0309",
          "lessonIndex": 109
        },
        {
          "classNo": "S27",
          "lessonType": "Tutorial",
          "weeks": [4, 6, 8, 10, 12],
          "day": "Thursday",
          "startTime": "1400",
          "endTime": "1600",
          "venue": "S16-0309",
          "lessonIndex": 110
        },
        {
          "classNo": "S28",
          "lessonType": "Tutorial",
          "weeks": [4, 6, 8, 10, 12],
          "day": "Thursday",
          "startTime": "1000",
          "endTime": "1200",
          "venue": "S16-0437",
          "lessonIndex": 111
        },
        {
          "classNo": "S29",
          "lessonType": "Tutorial",
          "weeks": [3, 5, 7, 9, 11],
          "day": "Monday",
          "startTime": "1200",
          "endTime": "1400",
          "venue": "S16-0309",
          "lessonIndex": 112
        },
        {
          "classNo": "S30",
          "lessonType": "Tutorial",
          "weeks": [4, 6, 8, 10, 12],
          "day": "Monday",
          "startTime": "1200",
          "endTime": "1400",
          "venue": "S16-0309",
          "lessonIndex": 113
        },
        {
          "classNo": "U01",
          "lessonType": "Tutorial",
          "weeks": [3, 5, 7, 9, 11],
          "day": "Monday",
          "startTime": "1400",
          "endTime": "1600",
          "venue": "TP-SR9",
          "lessonIndex": 114
        },
        {
          "classNo": "U02",
          "lessonType": "Tutorial",
          "weeks": [4, 6, 8, 10, 12],
          "day": "Monday",
          "startTime": "1400",
          "endTime": "1600",
          "venue": "TP-SR9",
          "lessonIndex": 115
        },
        {
          "classNo": "U03",
          "lessonType": "Tutorial",
          "weeks": [3, 5, 7, 9, 11],
          "day": "Tuesday",
          "startTime": "1600",
          "endTime": "1800",
          "venue": "UTSRC-GLR",
          "lessonIndex": 116
        },
        {
          "classNo": "U04",
          "lessonType": "Tutorial",
          "weeks": [4, 6, 8, 10, 12],
          "day": "Tuesday",
          "startTime": "1600",
          "endTime": "1800",
          "venue": "UTSRC-GLR",
          "lessonIndex": 117
        },
        {
          "classNo": "U05",
          "lessonType": "Tutorial",
          "weeks": [3, 5, 7, 9, 11],
          "day": "Wednesday",
          "startTime": "1200",
          "endTime": "1400",
          "venue": "ERC-SR9CAM",
          "lessonIndex": 118
        },
        {
          "classNo": "U06",
          "lessonType": "Tutorial",
          "weeks": [4, 6, 8, 10, 12],
          "day": "Wednesday",
          "startTime": "1200",
          "endTime": "1400",
          "venue": "ERC-SR9CAM",
          "lessonIndex": 119
        },
        {
          "classNo": "U07",
          "lessonType": "Tutorial",
          "weeks": [3, 5, 7, 9, 11],
          "day": "Wednesday",
          "startTime": "1200",
          "endTime": "1400",
          "venue": "ERC-SR10",
          "lessonIndex": 120
        },
        {
          "classNo": "U08",
          "lessonType": "Tutorial",
          "weeks": [4, 6, 8, 10, 12],
          "day": "Wednesday",
          "startTime": "1200",
          "endTime": "1400",
          "venue": "ERC-SR10",
          "lessonIndex": 121
        },
        {
          "classNo": "U09",
          "lessonType": "Tutorial",
          "weeks": [4, 6, 8, 10, 12],
          "day": "Thursday",
          "startTime": "0800",
          "endTime": "1000",
          "venue": "ERC-SR8",
          "lessonIndex": 122
        },
        {
          "classNo": "U10",
          "lessonType": "Tutorial",
          "weeks": [4, 6, 8, 10, 12],
          "day": "Thursday",
          "startTime": "1000",
          "endTime": "1200",
          "venue": "UTSRC-GLR",
          "lessonIndex": 123
        },
        {
          "classNo": "U11",
          "lessonType": "Tutorial",
          "weeks": [3, 5, 7, 9, 11],
          "day": "Tuesday",
          "startTime": "1900",
          "endTime": "2100",
          "venue": "TP-SR9",
          "lessonIndex": 124
        },
        {
          "classNo": "U12",
          "lessonType": "Tutorial",
          "weeks": [4, 6, 8, 10, 12],
          "day": "Tuesday",
          "startTime": "1900",
          "endTime": "2100",
          "venue": "TP-SR9",
          "lessonIndex": 125
        },
        {
          "classNo": "U13",
          "lessonType": "Tutorial",
          "weeks": [3, 5, 7, 9, 11],
          "day": "Wednesday",
          "startTime": "1900",
          "endTime": "2100",
          "venue": "ERC-SR8",
          "lessonIndex": 126
        },
        {
          "classNo": "U14",
          "lessonType": "Tutorial",
          "weeks": [4, 6, 8, 10, 12],
          "day": "Wednesday",
          "startTime": "1900",
          "endTime": "2100",
          "venue": "ERC-SR8",
          "lessonIndex": 127
        },
        {
          "classNo": "U15",
          "lessonType": "Tutorial",
          "weeks": [3, 5, 7, 9, 11],
          "day": "Wednesday",
          "startTime": "1600",
          "endTime": "1800",
          "venue": "UTSRC-GLR",
          "lessonIndex": 128
        },
        {
          "classNo": "U16",
          "lessonType": "Tutorial",
          "weeks": [4, 6, 8, 10, 12],
          "day": "Wednesday",
          "startTime": "1600",
          "endTime": "1800",
          "venue": "UTSRC-GLR",
          "lessonIndex": 129
        }
      ]
    }
  ],
  "fulfillRequirements": [
    "PR3144"
  ]
}
